README.md
setup.cfg
setup.py
pyGoDaddyUpdater/__init__.py
pyGoDaddyUpdater/__main__.py
pyGoDaddyUpdater.egg-info/PKG-INFO
pyGoDaddyUpdater.egg-info/SOURCES.txt
pyGoDaddyUpdater.egg-info/dependency_links.txt
pyGoDaddyUpdater.egg-info/entry_points.txt
pyGoDaddyUpdater.egg-info/requires.txt
pyGoDaddyUpdater.egg-info/top_level.txt
pyGoDaddyUpdater.egg-info/zip-safe
pyGoDaddyUpdater/logging_utils/__init__.py
pyGoDaddyUpdater/logging_utils/utils.py
pyGoDaddyUpdater/network/__init__.py
pyGoDaddyUpdater/network/network_utils.py
pyGoDaddyUpdater/preferences/__init__.py
pyGoDaddyUpdater/preferences/user_preferences.py
pyGoDaddyUpdater/values/__init__.py
pyGoDaddyUpdater/values/constants.py